dco_check/__init__.py
dco_check/dco_check.py
dco_check-0.5.0.dist-info/LICENSE
dco_check-0.5.0.dist-info/METADATA
dco_check-0.5.0.dist-info/WHEEL
dco_check-0.5.0.dist-info/entry_points.txt
dco_check-0.5.0.dist-info/top_level.txt
dco_check-0.5.0.dist-info/zip-safe
dco_check-0.5.0.dist-info/RECORD
