Metadata-Version: 2.1
Name: dco-check
Version: 0.5.0
Summary: Simple DCO check script to be used in any CI.
Home-page: https://github.com/christophebedard/dco-check/
Author: Christophe Bedard
Author-email: bedard.christophe@gmail.com
Maintainer: Christophe Bedard
Maintainer-email: bedard.christophe@gmail.com
License: Apache License, Version 2.0
Project-URL: Changelog, https://github.com/christophebedard/dco-check/milestones?state=closed
Project-URL: GitHub, https://github.com/christophebedard/dco-check/
Keywords: dco,check
Classifier: Development Status :: 3 - Alpha
Classifier: Intended Audience :: Developers
Classifier: License :: OSI Approved :: Apache Software License
Classifier: Operating System :: POSIX
Classifier: Programming Language :: Python
Classifier: Programming Language :: Python :: 3.8
Classifier: Programming Language :: Python :: 3.9
Classifier: Programming Language :: Python :: 3.10
Classifier: Programming Language :: Python :: 3.11
Classifier: Programming Language :: Python :: 3.12
Classifier: Topic :: Software Development :: Libraries :: Python Modules
Classifier: Topic :: Software Development :: Testing
License-File: LICENSE
